qrcode_song/__init__.py
qrcode_song/myqrcode.py
qrcode_song-0.3.dist-info/METADATA
qrcode_song-0.3.dist-info/RECORD
qrcode_song-0.3.dist-info/WHEEL
qrcode_song-0.3.dist-info/top_level.txt
